code_vision_cli/__init__.py
code_vision_cli/__main__.py
code_vision_cli/loader/__init__.py
code_vision_cli/loader/filter.py
code_vision_cli/loader/helper.py
code_vision_cli/loader/load.py
code_vision_cli/result/__init__.py
code_vision_cli/result/cluster.py
code_vision_cli/similarity/__init__.py
code_vision_cli/similarity/jaccard.py
code_vision_cli/similarity/lcs.py
code_vision_cli/similarity/similarity.py
code_vision_cli-0.1.6.dist-info/LICENSE
code_vision_cli-0.1.6.dist-info/METADATA
code_vision_cli-0.1.6.dist-info/WHEEL
code_vision_cli-0.1.6.dist-info/entry_points.txt
code_vision_cli-0.1.6.dist-info/top_level.txt
code_vision_cli-0.1.6.dist-info/RECORD
