Metadata-Version: 2.1
Name: code-vision-cli
Version: 0.1.6
Summary: Code Vision
Home-page: 
Author: Saeed Anabtawi
License: MIT
Project-URL: GitHub, https://github.com/saeedanabtawi/code-vision-cli
Classifier: Intended Audience :: Developers
Classifier: License :: OSI Approved :: MIT License
Classifier: Programming Language :: Python
Classifier: Programming Language :: Python :: 3.11
Classifier: Operating System :: OS Independent
License-File: LICENSE
Requires-Dist: networkx
Requires-Dist: matplotlib
Requires-Dist: argparse
Requires-Dist: pycparser
Requires-Dist: tqdm
